barnyard/PK_generator.py
barnyard/__init__.py
barnyard/core.py
barnyard/days_ago.py
barnyard/main.py
barnyard/max_time.py
barnyard/mini_guide.py
barnyard/next_number.py
barnyard/others.py
barnyard/run_func_with_timeout.py
barnyard/since_when.py
barnyard/validations.py
barnyard/cleandb/__init__.py
barnyard/cleandb/archive.py
barnyard/cleandb/main.py
barnyard/cleandb/mdb_ScreenBuffer.py
barnyard/cleandb/mdb_control_file_visibility.py
barnyard/cleandb/mdb_core.py
barnyard/cleandb/mdb_date_change.py
barnyard/cleandb/mdb_future_datetime.py
barnyard/cleandb/mdb_how_long.py
barnyard/cleandb/mdb_loop_progress.py
barnyard/cleandb/mdb_max_clear.py
barnyard/cleandb/mdb_mini_guide.py
barnyard/cleandb/mdb_others.py
barnyard/cleandb/mdb_pretty_print.py
barnyard/cleandb/mdb_session_id_generator.py
barnyard/cleandb/mdb_validations.py
barnyard/cleandb/mdb_wait_queue.py
barnyard/syngate/__init__.py
barnyard/syngate/main.py
barnyard/syngate/session_id_generator.py
barnyard/syngate/syngate_withopen/__init__.py
barnyard/syngate/syngate_withopen/archive.py
barnyard/syngate/syngate_withopen/main.py
barnyard/syngate/syngate_withopen/mdb_ScreenBuffer.py
barnyard/syngate/syngate_withopen/mdb_control_file_visibility.py
barnyard/syngate/syngate_withopen/mdb_core.py
barnyard/syngate/syngate_withopen/mdb_date_change.py
barnyard/syngate/syngate_withopen/mdb_future_datetime.py
barnyard/syngate/syngate_withopen/mdb_how_long.py
barnyard/syngate/syngate_withopen/mdb_loop_progress.py
barnyard/syngate/syngate_withopen/mdb_max_clear.py
barnyard/syngate/syngate_withopen/mdb_mini_guide.py
barnyard/syngate/syngate_withopen/mdb_others.py
barnyard/syngate/syngate_withopen/mdb_pretty_print.py
barnyard/syngate/syngate_withopen/mdb_session_id_generator.py
barnyard/syngate/syngate_withopen/mdb_validations.py
barnyard/syngate/syngate_withopen/mdb_wait_queue.py
barnyard-3.6.0.dist-info/licenses/LICENSE
barnyard-3.6.0.dist-info/METADATA
barnyard-3.6.0.dist-info/WHEEL
barnyard-3.6.0.dist-info/top_level.txt
barnyard-3.6.0.dist-info/RECORD
