Metadata-Version: 2.4
Name: barnyard
Version: 3.6.0
Summary: Temporary Delete System for Safe Batch Automation and Lead Distribution
Author: Henry
Author-email: osas2henry@gmail.com
License: MIT
Keywords: automation batch processing deletion safety recovery leads
Classifier: Development Status :: 5 - Production/Stable
Classifier: Intended Audience :: Developers
Classifier: License :: OSI Approved :: MIT License
Classifier: Programming Language :: Python :: 3
Classifier: Topic :: Software Development :: Libraries :: Python Modules
Requires-Python: >=3.7
License-File: LICENSE
Dynamic: author
Dynamic: author-email
Dynamic: classifier
Dynamic: description
Dynamic: description-content-type
Dynamic: keywords
Dynamic: license
Dynamic: license-file
Dynamic: requires-python
Dynamic: summary
